CONTRIBUTORS.txt
HISTORY.txt
LICENSE
MANIFEST.in
README.md
ez_setup.py
setup.py
clonedigger/LICENSE.txt
clonedigger/README.txt
clonedigger/__init__.py
clonedigger/abstract_syntax_tree.py
clonedigger/anti_unification.py
clonedigger/arguments.py
clonedigger/ast_suppliers.py
clonedigger/clone_detection_algorithm.py
clonedigger/clonedigger.py
clonedigger/html_report.py
clonedigger/java_antlr.py
clonedigger/js_antlr.py
clonedigger/lua_antlr.py
clonedigger/python_compiler.py
clonedigger/suffix_tree.py
clonedigger/antlr_runtime/antlr-3.1.1.jar
clonedigger/antlr_runtime/antlr-runtime-3.1.jar
clonedigger/antlr_runtime/runtime-2008-01-10.16.jar
clonedigger/java_antlr/JavaAST.g
clonedigger/java_antlr/JavaAST.tokens
clonedigger/java_antlr/MyAstNode.java
clonedigger/java_antlr/MyAstNodeAdaptor.java
clonedigger/java_antlr/TreeProducer.jar
clonedigger/java_antlr/TreeProducer.java
clonedigger/java_antlr/build_jar.sh
clonedigger/js_antlr/JavaScript.g
clonedigger/js_antlr/JavaScript.tokens
clonedigger/js_antlr/JavaScriptLexer.java
clonedigger/js_antlr/JavaScriptParser.java
clonedigger/js_antlr/MyAstNode.java
clonedigger/js_antlr/MyAstNodeAdaptor.java
clonedigger/js_antlr/TreeProducer.jar
clonedigger/js_antlr/TreeProducer.java
clonedigger/js_antlr/build_jar.sh
clonedigger/js_antlr/license.txt
clonedigger/logilab/__init__.py
clonedigger/logilab/astng/__init__.py
clonedigger/logilab/astng/__pkginfo__.py
clonedigger/logilab/astng/_exceptions.py
clonedigger/logilab/astng/astutils.py
clonedigger/logilab/astng/builder.py
clonedigger/logilab/astng/inference.py
clonedigger/logilab/astng/inspector.py
clonedigger/logilab/astng/lookup.py
clonedigger/logilab/astng/manager.py
clonedigger/logilab/astng/nodes.py
clonedigger/logilab/astng/raw_building.py
clonedigger/logilab/astng/scoped_nodes.py
clonedigger/logilab/astng/utils.py
clonedigger/logilab/common/__init__.py
clonedigger/logilab/common/__pkginfo__.py
clonedigger/logilab/common/adbh.py
clonedigger/logilab/common/astutils.py
clonedigger_jl.egg-info/PKG-INFO
clonedigger_jl.egg-info/SOURCES.txt
clonedigger_jl.egg-info/dependency_links.txt
clonedigger_jl.egg-info/entry_points.txt
clonedigger_jl.egg-info/not-zip-safe
clonedigger_jl.egg-info/requires.txt
clonedigger_jl.egg-info/top_level.txt