Metadata-Version: 1.1
Name: clonedigger-jl
Version: 1.0.7
Summary: Clone Digger aimed to detect similar code in Python and Java programs.
Home-page: https://github.com/jlachowski/clonedigger
Author: Jaroslaw Lachowski
Author-email: jalachowski@gmail.com
License: GPL
Keywords: buildout buildbot
Platform: UNKNOWN
Classifier: Intended Audience :: Developers
Classifier: Topic :: Software Development :: Libraries :: Python Modules
